<?xml version="1.0" encoding="UTF-8"?>
<!DOCTYPE rules SYSTEM "https://resources.jetbrains.com/writerside/1.0/redirection-rules.dtd">
<rules>
    <!-- format is as follows
    <rule id="<unique id>">
        <accepts>page.html</accepts>
    </rule>
    -->
    <rule id="147f3b3a">
        <description>Created after removal of "리소스 관리" from Dlab Flow Docs</description>
        <accepts>resource.html</accepts>
    </rule>
    <rule id="719ae557">
        <description><![CDATA[Created after removal of "<resource-mng.md>" from Dlab Flow Docs]]></description>
        <accepts>resource-mng.html</accepts>
    </rule>
    <rule id="352638f4">
        <description>Created after removal of "데이터셋 관리" from Dlab Flow Docs</description>
        <accepts>dataset=mng.html</accepts>
    </rule>
    <rule id="86685c6">
        <description>Created after removal of "데이터셋 관리" from Dlab Flow Docs</description>
        <accepts>dataset-mng.html</accepts>
    </rule>
    <rule id="34462b0b">
        <description>Created after removal of "Overview" from Dlab Flow Docs</description>
        <accepts>Overview.html</accepts>
    </rule>
    <rule id="3cc38f36">
        <description>Created after removal of "Reference" from Dlab Flow Docs</description>
        <accepts>Reference.html</accepts>
    </rule>
    <rule id="45fa4f55">
        <description>Created after removal of "새로운 주제 만들어 보기" from Dlab Flow Docs</description>
        <accepts>new-topic-test.html</accepts>
    </rule>
    <rule id="4f71099c">
        <description>Created after removal of "테스트" from Dlab Flow Docs</description>
        <accepts>test.html</accepts>
    </rule>
    <rule id="29e6cc2d">
        <description>Created after removal of "How to" from Dlab Flow Docs</description>
        <accepts>How-to.html</accepts>
    </rule>
    <rule id="2f426982">
        <description>Created after removal of "Tutorial" from Dlab Flow Docs</description>
        <accepts>Tutorial.html</accepts>
    </rule>
    <rule id="4744a8f0">
        <description>Created after removal of "데이터셋 선택" from Dlab Flow Docs</description>
        <accepts>dataset-sellect.html</accepts>
    </rule>
</rules>